CALM_pytorch/CALM.py
CALM_pytorch/__init__.py
CALM_pytorch/sampling_utils.py
CALM_Pytorch-0.2.2.dist-info/LICENSE
CALM_Pytorch-0.2.2.dist-info/METADATA
CALM_Pytorch-0.2.2.dist-info/WHEEL
CALM_Pytorch-0.2.2.dist-info/top_level.txt
CALM_Pytorch-0.2.2.dist-info/RECORD
