Metadata-Version: 2.1
Name: CALM-Pytorch
Version: 0.2.2
Summary: CALM - Pytorch
Home-page: https://github.com/lucidrains/CALM-pytorch
Author: Phil Wang
Author-email: lucidrains@gmail.com
License: MIT
Keywords: artificial intelligence,deep learning,composing LLMs
Classifier: Development Status :: 4 - Beta
Classifier: Intended Audience :: Developers
Classifier: Topic :: Scientific/Engineering :: Artificial Intelligence
Classifier: License :: OSI Approved :: MIT License
Classifier: Programming Language :: Python :: 3.6
License-File: LICENSE
Requires-Dist: accelerate
Requires-Dist: beartype
Requires-Dist: einops >=0.7.0
Requires-Dist: pytorch-custom-utils >=0.0.11
Requires-Dist: torch >=2.0
Requires-Dist: tqdm
Requires-Dist: x-transformers >=1.27.3
